motti/__init__.py
motti/color.py
motti/constant.py
motti/extension.py
motti/gpu.py
motti/model_info.py
motti/standard.py
motti-0.0.43.dist-info/LICENSE
motti-0.0.43.dist-info/METADATA
motti-0.0.43.dist-info/WHEEL
motti-0.0.43.dist-info/top_level.txt
motti-0.0.43.dist-info/RECORD
